etl_sync
