Metadata-Version: 1.1
Name: django-etl-sync
Version: 0.3.3
Summary: Django ETL, derives rules from models, creates relations.
Home-page: https://github.com/postfalk/django-etl-sync.git
Author: Falk Schuetzenmeister
Author-email: schuetzenmeister@berkeley.edu
License: BSD License
Download-URL: https://github.com/postfalk/django-etl-sync/tarball/0.3.3
Platform: UNKNOWN
Classifier: Development Status :: 4 - Beta
Classifier: Intended Audience :: Developers
Classifier: Environment :: Web Environment
Classifier: Framework :: Django
Classifier: Framework :: Django :: 1.7
Classifier: Framework :: Django :: 1.8
Classifier: Framework :: Django :: 1.9
Classifier: Framework :: Django :: 2.0
Classifier: Intended Audience :: Developers
Classifier: License :: OSI Approved :: BSD License
Classifier: Operating System :: OS Independent
Classifier: Programming Language :: Python
Classifier: Programming Language :: Python :: 2.7
Classifier: Programming Language :: Python :: 3.6
Classifier: Topic :: Internet :: WWW/HTTP
Classifier: Topic :: Internet :: WWW/HTTP :: Dynamic Content
